drawio_parser/__init__.py
drawio_parser/component.py
drawio_parser/diagram.py
drawio_parser/parser.py
drawio_parser-0.0.7.dist-info/METADATA
drawio_parser-0.0.7.dist-info/WHEEL
drawio_parser-0.0.7.dist-info/top_level.txt
drawio_parser-0.0.7.dist-info/RECORD
