Metadata-Version: 2.1
Name: drawio-parser
Version: 0.0.7
Summary: A drawio file parser
Home-page: https://github.com/pypa/sampleproject
Author: Rafael Freire
Author-email: rafaeldemaio@gmail.com
License: UNKNOWN
Project-URL: Issues Tracker, https://git.cvc.com.br/architecture/backend-platform/libraries/python/drawio-parser/issues
Platform: UNKNOWN
Classifier: Programming Language :: Python :: 3
Classifier: License :: OSI Approved :: MIT License
Classifier: Operating System :: OS Independent
Requires-Python: >=3.6
